Spark202ZhongwenWendang/README.md
Spark202ZhongwenWendang/__init__.py
Spark202ZhongwenWendang/__main__.py
Spark202ZhongwenWendang/file.epub
Spark202ZhongwenWendang/index.html
Spark202ZhongwenWendang/css/__init__.py
Spark202ZhongwenWendang/css/annotations.css
Spark202ZhongwenWendang/css/main.css
Spark202ZhongwenWendang/css/normalize.css
Spark202ZhongwenWendang/css/popup.css
Spark202ZhongwenWendang/font/__init__.py
Spark202ZhongwenWendang/font/fontello.eot
Spark202ZhongwenWendang/font/fontello.svg
Spark202ZhongwenWendang/font/fontello.ttf
Spark202ZhongwenWendang/font/fontello.woff
Spark202ZhongwenWendang/img/__init__.py
Spark202ZhongwenWendang/img/annotator-glyph-sprite.png
Spark202ZhongwenWendang/img/annotator-icon-sprite.png
Spark202ZhongwenWendang/img/apple-touch-icon.png
Spark202ZhongwenWendang/img/cancelfullscreen.png
Spark202ZhongwenWendang/img/close.png
Spark202ZhongwenWendang/img/fullscreen.png
Spark202ZhongwenWendang/img/loader.gif
Spark202ZhongwenWendang/img/menu-icon.png
Spark202ZhongwenWendang/img/save.png
Spark202ZhongwenWendang/img/saved.png
Spark202ZhongwenWendang/img/settings-s.png
Spark202ZhongwenWendang/img/settings.png
Spark202ZhongwenWendang/img/star.png
Spark202ZhongwenWendang/js/__init__.py
Spark202ZhongwenWendang/js/epub.js
Spark202ZhongwenWendang/js/epub.min.js
Spark202ZhongwenWendang/js/epub.min.map
Spark202ZhongwenWendang/js/hooks.min.js
Spark202ZhongwenWendang/js/hooks.min.map
Spark202ZhongwenWendang/js/reader.js
Spark202ZhongwenWendang/js/reader.js.map
Spark202ZhongwenWendang/js/reader.min.js
Spark202ZhongwenWendang/js/reader.min.map
Spark202ZhongwenWendang/js/hooks/__init__.py
Spark202ZhongwenWendang/js/hooks/extensions/__init__.py
Spark202ZhongwenWendang/js/hooks/extensions/highlight.js
Spark202ZhongwenWendang/js/libs/__init__.py
Spark202ZhongwenWendang/js/libs/jquery.min.js
Spark202ZhongwenWendang/js/libs/localforage.min.js
Spark202ZhongwenWendang/js/libs/screenfull.js
Spark202ZhongwenWendang/js/libs/screenfull.min.js
spark_2_0_2_zhongwen_wendang-2024.3.2.0.dist-info/METADATA
spark_2_0_2_zhongwen_wendang-2024.3.2.0.dist-info/WHEEL
spark_2_0_2_zhongwen_wendang-2024.3.2.0.dist-info/entry_points.txt
spark_2_0_2_zhongwen_wendang-2024.3.2.0.dist-info/top_level.txt
spark_2_0_2_zhongwen_wendang-2024.3.2.0.dist-info/RECORD
